{
  "users": [
    {
      "id": 1,
      "name": "Leanne Graham",
      "email": "Sincere@april.biz",
      "address": "Kulas Light",
      "phone": "1-770-736-8031 x56442"
    },
    {
      "id": 2,
      "name": "Leanne Graham",
      "email": "Sincere@april.biz",
      "address": "Kulas Light",
      "phone": "1-770-736-8031 x56442"
    },
    {
      "id": 3,
      "name": "Leanne Graham",
      "email": "Sincere@april.biz",
      "address": "Kulas Light",
      "phone": "1-770-736-8031 x56442"
    },
    {
      "id": 4,
      "name": "Leanne Graham",
      "email": "Sincere@april.biz",
      "address": "Kulas Light",
      "phone": "1-770-736-8031 x56442"
    },
    {
      "id": 5,
      "name": "Leanne Graham",
      "email": "Sincere@april.biz",
      "address": "Kulas Light",
      "phone": "1-770-736-8031 x56442"
    },
    {
      "id": 6,
      "name": "Leanne Graham",
      "email": "Sincere@april.biz",
      "address": "Kulas Light",
      "phone": "1-770-736-8031 x56442"
    },
    {
      "id": 7,
      "name": "Leanne Graham",
      "email": "Sincere@april.biz",
      "address": "Kulas Light",
      "phone": "1-770-736-8031 x56442"
    },
    {
      "id": 8,
      "name": "Leanne Graham",
      "email": "Sincere@april.biz",
      "address": "Kulas Light",
      "phone": "1-770-736-8031 x56442"
    },
    {
      "id": 9,
      "name": "Leanne Graham",
      "email": "Sincere@april.biz",
      "address": "Kulas Light",
      "phone": "1-770-736-8031 x56442"
    },
    {
      "id": 10,
      "name": "Leanne Graham",
      "email": "Sincere@april.biz",
      "address": "Kulas Light",
      "phone": "1-770-736-8031 x56442"
    },
    {
      "id": 11,
      "name": "Leanne Graham",
      "email": "Sincere@april.biz",
      "address": "Kulas Light",
      "phone": "1-770-736-8031 x56442"
    },
    {
      "id": 12,
      "name": "Leanne Graham",
      "email": "Sincere@april.biz",
      "address": "Kulas Light",
      "phone": "1-770-736-8031 x56442"
    },
    {
      "id": 13,
      "name": "Leanne Graham",
      "email": "Sincere@april.biz",
      "address": "Kulas Light",
      "phone": "1-770-736-8031 x56442"
    },
    {
      "id": 14,
      "name": "Leanne Graham",
      "email": "Sincere@april.biz",
      "address": "Kulas Light",
      "phone": "1-770-736-8031 x56442"
    },
    {
      "id": 15,
      "name": "Leanne Graham",
      "email": "Sincere@april.biz",
      "address": "Kulas Light",
      "phone": "1-770-736-8031 x56442"
    },
    {
      "id": 16,
      "name": "Leanne Graham",
      "email": "Sincere@april.biz",
      "address": "Kulas Light",
      "phone": "1-770-736-8031 x56442"
    }
  ]
}